boring/__init__.py
boring/__main__.py
boring/auto_fix.py
boring/background_agent.py
boring/backup.py
boring/brain_manager.py
boring/cache.py
boring/circuit.py
boring/cli_client.py
boring/config.py
boring/constants.py
boring/context_selector.py
boring/context_sync.py
boring/dashboard.py
boring/debugger.py
boring/diff_patcher.py
boring/error_diagnostics.py
boring/error_translator.py
boring/exceptions.py
boring/extensions.py
boring/feedback_learner.py
boring/file_patcher.py
boring/gemini_client.py
boring/health.py
boring/hooks.py
boring/interactions_client.py
boring/interactive.py
boring/interfaces.py
boring/limiter.py
boring/logger.py
boring/main.py
boring/memory.py
boring/models.py
boring/monitor.py
boring/paths.py
boring/py.typed
boring/quality_tracker.py
boring/quickstart.py
boring/response_analyzer.py
boring/rubrics.py
boring/security.py
boring/setup.py
boring/shadow_mode.py
boring/skills_catalog.py
boring/storage.py
boring/streaming.py
boring/transactions.py
boring/trust_rules.py
boring/tutorial.py
boring/types.py
boring/vscode_server.py
boring/web_monitor.py
boring/workflow_manager.py
boring/workspace.py
boring/agents/__init__.py
boring/agents/bus.py
boring/agents/orchestrator.py
boring/agents/protocol.py
boring/agents/runner.py
boring/cli/__init__.py
boring/cli/audit.py
boring/cli/brain.py
boring/cli/cli_client.py
boring/cli/dashboard.py
boring/cli/dashboard_tui.py
boring/cli/doctor.py
boring/cli/installer.py
boring/cli/interactive.py
boring/cli/model.py
boring/cli/offline.py
boring/cli/onboard.py
boring/cli/packer.py
boring/cli/publisher.py
boring/cli/quickstart.py
boring/cli/rag.py
boring/cli/setup.py
boring/cli/suggestions.py
boring/cli/sync.py
boring/cli/theme.py
boring/cli/tui.py
boring/cli/tutorial.py
boring/cli/watch.py
boring/cli/wizard.py
boring/core/__init__.py
boring/core/cache.py
boring/core/circuit.py
boring/core/config.py
boring/core/constants.py
boring/core/context.py
boring/core/dependencies.py
boring/core/environment.py
boring/core/events.py
boring_aicoding-15.0.0.dist-info/licenses/LICENSE
boring_aicoding-15.0.0.dist-info/licenses/NOTICE
boring_aicoding-15.0.0.dist-info/METADATA
boring_aicoding-15.0.0.dist-info/WHEEL
boring_aicoding-15.0.0.dist-info/entry_points.txt
boring_aicoding-15.0.0.dist-info/top_level.txt
boring_aicoding-15.0.0.dist-info/RECORD
