Metadata-Version: 2.4
Name: boring-aicoding
Version: 15.0.0
Summary: Boring: An AI-powered development support tool for autonomous reasoning, planning, and verification. Optimized for uv and agentic workflows.
Author-email: Boring206 <C112156246@nkust.edu.tw>
Project-URL: Homepage, https://github.com/Boring206/boring-gemini
Project-URL: Repository, https://github.com/Boring206/boring-gemini
Project-URL: Documentation, https://github.com/Boring206/boring-gemini#readme
Project-URL: Bug Tracker, https://github.com/Boring206/boring-gemini/issues
Keywords: gemini,ai,autonomous-agent,devops
Classifier: Development Status :: 5 - Production/Stable
Classifier: Intended Audience :: Developers
Classifier: Programming Language :: Python :: 3
Classifier: Programming Language :: Python :: 3.10
Classifier: Programming Language :: Python :: 3.11
Classifier: Programming Language :: Python :: 3.12
Classifier: License :: OSI Approved :: Apache Software License
Classifier: Operating System :: OS Independent
Classifier: Topic :: Software Development :: Build Tools
Classifier: Topic :: Scientific/Engineering :: Artificial Intelligence
Classifier: Framework :: Pytest
Requires-Python: >=3.10
License-File: LICENSE
License-File: NOTICE
Requires-Dist: typer[all]>=0.9.0
Requires-Dist: rich>=13.0.0
Requires-Dist: python-dotenv
Requires-Dist: google-genai>=1.0.0
Requires-Dist: python-dateutil
Requires-Dist: gitpython
Requires-Dist: pydantic-settings>=2.0.0
Requires-Dist: structlog>=24.0.0
Requires-Dist: tenacity>=8.0.0
Requires-Dist: duckduckgo-search>=5.0.0
Requires-Dist: requests
Requires-Dist: watchdog>=3.0.0
Requires-Dist: toml>=0.10.0
Requires-Dist: tomlkit>=0.12.0
Provides-Extra: gui
Requires-Dist: streamlit>=1.30.0; extra == "gui"
Requires-Dist: pyarrow; extra == "gui"
Provides-Extra: dev
Requires-Dist: pytest>=7.0.0; extra == "dev"
Requires-Dist: pytest-asyncio>=0.21.0; extra == "dev"
Requires-Dist: pytest-mock>=3.0.0; extra == "dev"
Requires-Dist: pytest-cov>=4.0.0; extra == "dev"
Requires-Dist: ruff>=0.1.0; extra == "dev"
Requires-Dist: mypy>=1.0.0; extra == "dev"
Requires-Dist: types-python-dateutil; extra == "dev"
Requires-Dist: types-requests; extra == "dev"
Requires-Dist: radon>=6.0.0; extra == "dev"
Requires-Dist: interrogate>=1.5.0; extra == "dev"
Requires-Dist: bandit>=1.7.0; extra == "dev"
Requires-Dist: pip-audit>=2.7.0; extra == "dev"
Requires-Dist: mkdocs>=1.5.0; extra == "dev"
Requires-Dist: mkdocs-material>=9.5.0; extra == "dev"
Requires-Dist: mkdocstrings[python]>=0.24.0; extra == "dev"
Requires-Dist: psutil>=5.9.0; extra == "dev"
Requires-Dist: numpy>=1.26.0; extra == "dev"
Provides-Extra: vector
Requires-Dist: chromadb>=0.4.0; extra == "vector"
Requires-Dist: faiss-cpu>=1.7.4; extra == "vector"
Requires-Dist: sentence-transformers>=2.2.0; extra == "vector"
Requires-Dist: tree-sitter-languages==1.10.2; extra == "vector"
Requires-Dist: tree-sitter==0.25.2; extra == "vector"
Provides-Extra: mcp-lite
Requires-Dist: fastmcp>=2.0.0; extra == "mcp-lite"
Requires-Dist: mcp>=1.15.0; extra == "mcp-lite"
Requires-Dist: smithery>=0.4.2; extra == "mcp-lite"
Requires-Dist: uvicorn>=0.30.0; extra == "mcp-lite"
Requires-Dist: starlette>=0.37.0; extra == "mcp-lite"
Requires-Dist: bandit>=1.7.0; extra == "mcp-lite"
Requires-Dist: pip-audit>=2.7.0; extra == "mcp-lite"
Provides-Extra: mcp
Requires-Dist: boring-aicoding[mcp-lite]; extra == "mcp"
Requires-Dist: chromadb>=0.4.0; extra == "mcp"
Requires-Dist: faiss-cpu>=1.7.4; extra == "mcp"
Requires-Dist: sentence-transformers>=2.2.0; extra == "mcp"
Requires-Dist: win10toast>=0.9; platform_system == "Windows" and extra == "mcp"
Provides-Extra: local
Requires-Dist: llama-cpp-python>=0.2.50; extra == "local"
Requires-Dist: onnxruntime>=1.16.0; extra == "local"
Provides-Extra: all
Requires-Dist: boring-aicoding[dev,gui,local,mcp,vector]; extra == "all"
Dynamic: license-file
